lineartest/__init__.py
lineartest/_log.py
lineartest/_util.py
lineartest/client.py
lineartest/schedule.py
lineartest-0.4.4.dist-info/LICENSE
lineartest-0.4.4.dist-info/METADATA
lineartest-0.4.4.dist-info/WHEEL
lineartest-0.4.4.dist-info/RECORD
