Metadata-Version: 2.1
Name: lineartest
Version: 0.4.4
Summary: A testing framework working with Starlette TestClient.
License: MIT
Author: Philip Fan
Author-email: topfyf@qq.com
Requires-Python: >=3.10,<4.0
Classifier: Development Status :: 4 - Beta
Classifier: Intended Audience :: Developers
Classifier: License :: OSI Approved :: MIT License
Classifier: Operating System :: OS Independent
Classifier: Programming Language :: Python :: 3
Classifier: Programming Language :: Python :: 3.10
Classifier: Programming Language :: Python :: 3.11
Classifier: Programming Language :: Python :: 3.12
Classifier: Programming Language :: Python :: 3 :: Only
Classifier: Programming Language :: Python :: 3.13
Requires-Dist: httpx (>=0.27.0,<0.28.0)
Requires-Dist: pydantic (>=2.6.4,<3.0.0)
Requires-Dist: pyyaml (>=6.0.1,<7.0.0)
